[
    {
        "danceability": 0.65,
        "energy": 0.822,
        "key": 2,
        "loudness": -5.852,
        "mode": 0,
        "speechiness": 0.0348,
        "acousticness": 0.00408,
        "instrumentalness": 0.000192,
        "liveness": 0.265,
        "valence": 0.487,
        "tempo": 116.985,
        "type": "audio_features",
        "id": "3O5qvnCWTwPJlnmSqyizV1",
        "uri": "spotify:track:3O5qvnCWTwPJlnmSqyizV1",
        "track_href": "https://api.spotify.com/v1/tracks/3O5qvnCWTwPJlnmSqyizV1",
        "analysis_url": "https://api.spotify.com/v1/audio-analysis/3O5qvnCWTwPJlnmSqyizV1",
        "duration_ms": 234359,
        "time_signature": 4
    },
    {
        "danceability": 0.587,
        "energy": 0.398,
        "key": 9,
        "loudness": -12.418,
        "mode": 0,
        "speechiness": 0.0299,
        "acousticness": 0.529,
        "instrumentalness": 2.85e-05,
        "liveness": 0.13,
        "valence": 0.771,
        "tempo": 81.594,
        "type": "audio_features",
        "id": "4YbZRFi4GH3YEzNYyljd8p",
        "uri": "spotify:track:4YbZRFi4GH3YEzNYyljd8p",
        "track_href": "https://api.spotify.com/v1/tracks/4YbZRFi4GH3YEzNYyljd8p",
        "analysis_url": "https://api.spotify.com/v1/audio-analysis/4YbZRFi4GH3YEzNYyljd8p",
        "duration_ms": 142200,
        "time_signature": 4
    },
    {
        "danceability": 0.431,
        "energy": 0.321,
        "key": 7,
        "loudness": -11.827,
        "mode": 1,
        "speechiness": 0.0289,
        "acousticness": 0.667,
        "instrumentalness": 0,
        "liveness": 0.192,
        "valence": 0.518,
        "tempo": 103.164,
        "type": "audio_features",
        "id": "5kA88W2SwVZiPb9rEwnQj6",
        "uri": "spotify:track:5kA88W2SwVZiPb9rEwnQj6",
        "track_href": "https://api.spotify.com/v1/tracks/5kA88W2SwVZiPb9rEwnQj6",
        "analysis_url": "https://api.spotify.com/v1/audio-analysis/5kA88W2SwVZiPb9rEwnQj6",
        "duration_ms": 162373,
        "time_signature": 3
    },
    {
        "danceability": 0.543,
        "energy": 0.492,
        "key": 7,
        "loudness": -7.432,
        "mode": 1,
        "speechiness": 0.156,
        "acousticness": 0.0739,
        "instrumentalness": 0,
        "liveness": 0.11,
        "valence": 0.107,
        "tempo": 220.099,
        "type": "audio_features",
        "id": "2fSW54bA6x2iWePU7rpCiP",
        "uri": "spotify:track:2fSW54bA6x2iWePU7rpCiP",
        "track_href": "https://api.spotify.com/v1/tracks/2fSW54bA6x2iWePU7rpCiP",
        "analysis_url": "https://api.spotify.com/v1/audio-analysis/2fSW54bA6x2iWePU7rpCiP",
        "duration_ms": 231298,
        "time_signature": 4
    },
    {
        "danceability": 0.271,
        "energy": 0.599,
        "key": 0,
        "loudness": -4.63,
        "mode": 1,
        "speechiness": 0.0326,
        "acousticness": 0.455,
        "instrumentalness": 3.08e-06,
        "liveness": 0.11,
        "valence": 0.705,
        "tempo": 136.169,
        "type": "audio_features",
        "id": "4vBDAxKllafwCMDWD76atv",
        "uri": "spotify:track:4vBDAxKllafwCMDWD76atv",
        "track_href": "https://api.spotify.com/v1/tracks/4vBDAxKllafwCMDWD76atv",
        "analysis_url": "https://api.spotify.com/v1/audio-analysis/4vBDAxKllafwCMDWD76atv",
        "duration_ms": 151560,
        "time_signature": 3
    },
    {
        "danceability": 0.389,
        "energy": 0.412,
        "key": 5,
        "loudness": -8.131,
        "mode": 1,
        "speechiness": 0.0304,
        "acousticness": 0.192,
        "instrumentalness": 3.11e-06,
        "liveness": 0.0936,
        "valence": 0.363,
        "tempo": 115.882,
        "type": "audio_features",
        "id": "6kFmfcqpy1ok5wfls2yCtZ",
        "uri": "spotify:track:6kFmfcqpy1ok5wfls2yCtZ",
        "track_href": "https://api.spotify.com/v1/tracks/6kFmfcqpy1ok5wfls2yCtZ",
        "analysis_url": "https://api.spotify.com/v1/audio-analysis/6kFmfcqpy1ok5wfls2yCtZ",
        "duration_ms": 171427,
        "time_signature": 4
    },
    {
        "danceability": 0.725,
        "energy": 0.373,
        "key": 10,
        "loudness": -15.925,
        "mode": 1,
        "speechiness": 0.0494,
        "acousticness": 0.613,
        "instrumentalness": 0.0202,
        "liveness": 0.118,
        "valence": 0.846,
        "tempo": 148.367,
        "type": "audio_features",
        "id": "7Jf323ttHKUnPylFWiaGl3",
        "uri": "spotify:track:7Jf323ttHKUnPylFWiaGl3",
        "track_href": "https://api.spotify.com/v1/tracks/7Jf323ttHKUnPylFWiaGl3",
        "analysis_url": "https://api.spotify.com/v1/audio-analysis/7Jf323ttHKUnPylFWiaGl3",
        "duration_ms": 169000,
        "time_signature": 4
    },
    {
        "danceability": 0.453,
        "energy": 0.502,
        "key": 8,
        "loudness": -9.613,
        "mode": 1,
        "speechiness": 0.0415,
        "acousticness": 0.646,
        "instrumentalness": 2.2e-05,
        "liveness": 0.189,
        "valence": 0.139,
        "tempo": 90.096,
        "type": "audio_features",
        "id": "7pfDqoJTf20w13DQf9uYO0",
        "uri": "spotify:track:7pfDqoJTf20w13DQf9uYO0",
        "track_href": "https://api.spotify.com/v1/tracks/7pfDqoJTf20w13DQf9uYO0",
        "analysis_url": "https://api.spotify.com/v1/audio-analysis/7pfDqoJTf20w13DQf9uYO0",
        "duration_ms": 201333,
        "time_signature": 4
    },
    {
        "danceability": 0.497,
        "energy": 0.677,
        "key": 3,
        "loudness": -7.864,
        "mode": 1,
        "speechiness": 0.042,
        "acousticness": 0.866,
        "instrumentalness": 0.735,
        "liveness": 0.182,
        "valence": 0.784,
        "tempo": 130.11,
        "type": "audio_features",
        "id": "0gqYQBiXksbJ8dMpkwy9ne",
        "uri": "spotify:track:0gqYQBiXksbJ8dMpkwy9ne",
        "track_href": "https://api.spotify.com/v1/tracks/0gqYQBiXksbJ8dMpkwy9ne",
        "analysis_url": "https://api.spotify.com/v1/audio-analysis/0gqYQBiXksbJ8dMpkwy9ne",
        "duration_ms": 111000,
        "time_signature": 4
    },
    {
        "danceability": 0.451,
        "energy": 0.721,
        "key": 2,
        "loudness": -13.575,
        "mode": 1,
        "speechiness": 0.0374,
        "acousticness": 0.37,
        "instrumentalness": 0,
        "liveness": 0.233,
        "valence": 0.764,
        "tempo": 129.503,
        "type": "audio_features",
        "id": "61lKkMxzobo0H9nJjzMicx",
        "uri": "spotify:track:61lKkMxzobo0H9nJjzMicx",
        "track_href": "https://api.spotify.com/v1/tracks/61lKkMxzobo0H9nJjzMicx",
        "analysis_url": "https://api.spotify.com/v1/audio-analysis/61lKkMxzobo0H9nJjzMicx",
        "duration_ms": 175827,
        "time_signature": 4
    },
    {
        "danceability": 0.752,
        "energy": 0.557,
        "key": 6,
        "loudness": -8.028,
        "mode": 0,
        "speechiness": 0.0744,
        "acousticness": 0.31,
        "instrumentalness": 0.457,
        "liveness": 0.12,
        "valence": 0.368,
        "tempo": 124.001,
        "type": "audio_features",
        "id": "70MpjyMj8Bxo6RRHiA4SkM",
        "uri": "spotify:track:70MpjyMj8Bxo6RRHiA4SkM",
        "track_href": "https://api.spotify.com/v1/tracks/70MpjyMj8Bxo6RRHiA4SkM",
        "analysis_url": "https://api.spotify.com/v1/audio-analysis/70MpjyMj8Bxo6RRHiA4SkM",
        "duration_ms": 190981,
        "time_signature": 4
    },
    {
        "danceability": 0.21,
        "energy": 0.254,
        "key": 4,
        "loudness": -11.831,
        "mode": 0,
        "speechiness": 0.0334,
        "acousticness": 0.989,
        "instrumentalness": 0.937,
        "liveness": 0.115,
        "valence": 0.139,
        "tempo": 87.643,
        "type": "audio_features",
        "id": "2pMjdKDxWMu7jMs9dhvrTu",
        "uri": "spotify:track:2pMjdKDxWMu7jMs9dhvrTu",
        "track_href": "https://api.spotify.com/v1/tracks/2pMjdKDxWMu7jMs9dhvrTu",
        "analysis_url": "https://api.spotify.com/v1/audio-analysis/2pMjdKDxWMu7jMs9dhvrTu",
        "duration_ms": 175200,
        "time_signature": 4
    },
    {
        "danceability": 0.466,
        "energy": 0.125,
        "key": 11,
        "loudness": -20.428,
        "mode": 0,
        "speechiness": 0.0372,
        "acousticness": 0.863,
        "instrumentalness": 0,
        "liveness": 0.121,
        "valence": 0.338,
        "tempo": 111.43,
        "type": "audio_features",
        "id": "7LAsDdinXejDwodvelVVTa",
        "uri": "spotify:track:7LAsDdinXejDwodvelVVTa",
        "track_href": "https://api.spotify.com/v1/tracks/7LAsDdinXejDwodvelVVTa",
        "analysis_url": "https://api.spotify.com/v1/audio-analysis/7LAsDdinXejDwodvelVVTa",
        "duration_ms": 182027,
        "time_signature": 1
    },
    {
        "danceability": 0.711,
        "energy": 0.0539,
        "key": 4,
        "loudness": -21.772,
        "mode": 0,
        "speechiness": 0.284,
        "acousticness": 0.546,
        "instrumentalness": 0,
        "liveness": 0.0822,
        "valence": 0.594,
        "tempo": 89.959,
        "type": "audio_features",
        "id": "0rbqKihC0VJq0INo8VB1oq",
        "uri": "spotify:track:0rbqKihC0VJq0INo8VB1oq",
        "track_href": "https://api.spotify.com/v1/tracks/0rbqKihC0VJq0INo8VB1oq",
        "analysis_url": "https://api.spotify.com/v1/audio-analysis/0rbqKihC0VJq0INo8VB1oq",
        "duration_ms": 47133,
        "time_signature": 1
    },
    {
        "danceability": 0.554,
        "energy": 0.925,
        "key": 4,
        "loudness": -8.163,
        "mode": 0,
        "speechiness": 0.0868,
        "acousticness": 0.00927,
        "instrumentalness": 0.0169,
        "liveness": 0.055,
        "valence": 0.638,
        "tempo": 193.79,
        "type": "audio_features",
        "id": "7N2qyJrAp16ghZFBloT8Ye",
        "uri": "spotify:track:7N2qyJrAp16ghZFBloT8Ye",
        "track_href": "https://api.spotify.com/v1/tracks/7N2qyJrAp16ghZFBloT8Ye",
        "analysis_url": "https://api.spotify.com/v1/audio-analysis/7N2qyJrAp16ghZFBloT8Ye",
        "duration_ms": 274960,
        "time_signature": 4
    },
    {
        "danceability": 0.663,
        "energy": 0.846,
        "key": 11,
        "loudness": -9.86,
        "mode": 1,
        "speechiness": 0.0415,
        "acousticness": 0.532,
        "instrumentalness": 0.658,
        "liveness": 0.25,
        "valence": 0.347,
        "tempo": 115.992,
        "type": "audio_features",
        "id": "0bOCFpsO4YCUp3Nbn68zAZ",
        "uri": "spotify:track:0bOCFpsO4YCUp3Nbn68zAZ",
        "track_href": "https://api.spotify.com/v1/tracks/0bOCFpsO4YCUp3Nbn68zAZ",
        "analysis_url": "https://api.spotify.com/v1/audio-analysis/0bOCFpsO4YCUp3Nbn68zAZ",
        "duration_ms": 102468,
        "time_signature": 4
    },
    {
        "danceability": 0.722,
        "energy": 0.835,
        "key": 8,
        "loudness": -5.433,
        "mode": 1,
        "speechiness": 0.0306,
        "acousticness": 0.146,
        "instrumentalness": 0.00147,
        "liveness": 0.0779,
        "valence": 0.789,
        "tempo": 106.845,
        "type": "audio_features",
        "id": "5aSzAqrAOtzYjWYj4YHJLz",
        "uri": "spotify:track:5aSzAqrAOtzYjWYj4YHJLz",
        "track_href": "https://api.spotify.com/v1/tracks/5aSzAqrAOtzYjWYj4YHJLz",
        "analysis_url": "https://api.spotify.com/v1/audio-analysis/5aSzAqrAOtzYjWYj4YHJLz",
        "duration_ms": 268333,
        "time_signature": 4
    },
    {
        "danceability": 0.637,
        "energy": 0.973,
        "key": 9,
        "loudness": -3.386,
        "mode": 1,
        "speechiness": 0.112,
        "acousticness": 0.000413,
        "instrumentalness": 2.23e-05,
        "liveness": 0.104,
        "valence": 0.8,
        "tempo": 150.223,
        "type": "audio_features",
        "id": "4OkPamOn5GofkOQu64Z4eR",
        "uri": "spotify:track:4OkPamOn5GofkOQu64Z4eR",
        "track_href": "https://api.spotify.com/v1/tracks/4OkPamOn5GofkOQu64Z4eR",
        "analysis_url": "https://api.spotify.com/v1/audio-analysis/4OkPamOn5GofkOQu64Z4eR",
        "duration_ms": 160640,
        "time_signature": 4
    },
    {
        "danceability": 0.541,
        "energy": 0.719,
        "key": 7,
        "loudness": -7.285,
        "mode": 0,
        "speechiness": 0.0326,
        "acousticness": 9.56e-05,
        "instrumentalness": 0.516,
        "liveness": 0.0725,
        "valence": 0.299,
        "tempo": 135.002,
        "type": "audio_features",
        "id": "4vnPiUc0uJRHnm7vRsrDls",
        "uri": "spotify:track:4vnPiUc0uJRHnm7vRsrDls",
        "track_href": "https://api.spotify.com/v1/tracks/4vnPiUc0uJRHnm7vRsrDls",
        "analysis_url": "https://api.spotify.com/v1/audio-analysis/4vnPiUc0uJRHnm7vRsrDls",
        "duration_ms": 262093,
        "time_signature": 3
    },
    {
        "danceability": 0.389,
        "energy": 0.962,
        "key": 2,
        "loudness": -4.772,
        "mode": 0,
        "speechiness": 0.248,
        "acousticness": 5.98e-05,
        "instrumentalness": 0.623,
        "liveness": 0.331,
        "valence": 0.155,
        "tempo": 183.049,
        "type": "audio_features",
        "id": "3ySqZ8yGoh4Emi9HiPCCdP",
        "uri": "spotify:track:3ySqZ8yGoh4Emi9HiPCCdP",
        "track_href": "https://api.spotify.com/v1/tracks/3ySqZ8yGoh4Emi9HiPCCdP",
        "analysis_url": "https://api.spotify.com/v1/audio-analysis/3ySqZ8yGoh4Emi9HiPCCdP",
        "duration_ms": 239864,
        "time_signature": 4
    },
    {
        "danceability": 0.458,
        "energy": 0.67,
        "key": 10,
        "loudness": -4.993,
        "mode": 1,
        "speechiness": 0.0397,
        "acousticness": 0.025,
        "instrumentalness": 3.78e-06,
        "liveness": 0.358,
        "valence": 0.107,
        "tempo": 160.05,
        "type": "audio_features",
        "id": "6huKKoWv2Xy4KM2rwUNa7X",
        "uri": "spotify:track:6huKKoWv2Xy4KM2rwUNa7X",
        "track_href": "https://api.spotify.com/v1/tracks/6huKKoWv2Xy4KM2rwUNa7X",
        "analysis_url": "https://api.spotify.com/v1/audio-analysis/6huKKoWv2Xy4KM2rwUNa7X",
        "duration_ms": 243028,
        "time_signature": 4
    },
    {
        "danceability": 0.588,
        "energy": 0.312,
        "key": 5,
        "loudness": -10.461,
        "mode": 1,
        "speechiness": 0.074,
        "acousticness": 0.947,
        "instrumentalness": 2.07e-05,
        "liveness": 0.445,
        "valence": 0.639,
        "tempo": 144.768,
        "type": "audio_features",
        "id": "7a5VuzvBrtbqYT7kNlQlFd",
        "uri": "spotify:track:7a5VuzvBrtbqYT7kNlQlFd",
        "track_href": "https://api.spotify.com/v1/tracks/7a5VuzvBrtbqYT7kNlQlFd",
        "analysis_url": "https://api.spotify.com/v1/audio-analysis/7a5VuzvBrtbqYT7kNlQlFd",
        "duration_ms": 206800,
        "time_signature": 4
    },
    {
        "danceability": 0.498,
        "energy": 0.625,
        "key": 11,
        "loudness": -8.639,
        "mode": 1,
        "speechiness": 0.0353,
        "acousticness": 0.551,
        "instrumentalness": 0.00172,
        "liveness": 0.25,
        "valence": 0.931,
        "tempo": 133.253,
        "type": "audio_features",
        "id": "71gEktT9oQK2YWgbLCa4Jo",
        "uri": "spotify:track:71gEktT9oQK2YWgbLCa4Jo",
        "track_href": "https://api.spotify.com/v1/tracks/71gEktT9oQK2YWgbLCa4Jo",
        "analysis_url": "https://api.spotify.com/v1/audio-analysis/71gEktT9oQK2YWgbLCa4Jo",
        "duration_ms": 163143,
        "time_signature": 4
    },
    {
        "danceability": 0.787,
        "energy": 0.63,
        "key": 0,
        "loudness": -12.295,
        "mode": 1,
        "speechiness": 0.0609,
        "acousticness": 0.0274,
        "instrumentalness": 6.69e-06,
        "liveness": 0.161,
        "valence": 0.882,
        "tempo": 125.347,
        "type": "audio_features",
        "id": "6J6RWKCPN5RFKHUKEUFjxS",
        "uri": "spotify:track:6J6RWKCPN5RFKHUKEUFjxS",
        "track_href": "https://api.spotify.com/v1/tracks/6J6RWKCPN5RFKHUKEUFjxS",
        "analysis_url": "https://api.spotify.com/v1/audio-analysis/6J6RWKCPN5RFKHUKEUFjxS",
        "duration_ms": 267293,
        "time_signature": 4
    },
    {
        "danceability": 0.497,
        "energy": 0.973,
        "key": 7,
        "loudness": -2.949,
        "mode": 1,
        "speechiness": 0.462,
        "acousticness": 0.0784,
        "instrumentalness": 8.09e-06,
        "liveness": 0.0946,
        "valence": 0.212,
        "tempo": 166.829,
        "type": "audio_features",
        "id": "6mSL6E1oxowyr3qknFAHTm",
        "uri": "spotify:track:6mSL6E1oxowyr3qknFAHTm",
        "track_href": "https://api.spotify.com/v1/tracks/6mSL6E1oxowyr3qknFAHTm",
        "analysis_url": "https://api.spotify.com/v1/audio-analysis/6mSL6E1oxowyr3qknFAHTm",
        "duration_ms": 173760,
        "time_signature": 4
    },
    {
        "danceability": 0.682,
        "energy": 0.666,
        "key": 4,
        "loudness": -10.041,
        "mode": 1,
        "speechiness": 0.0379,
        "acousticness": 0.538,
        "instrumentalness": 3.06e-05,
        "liveness": 0.0554,
        "valence": 0.932,
        "tempo": 125.066,
        "type": "audio_features",
        "id": "1oqxU521xW9h8rJWzVWxD4",
        "uri": "spotify:track:1oqxU521xW9h8rJWzVWxD4",
        "track_href": "https://api.spotify.com/v1/tracks/1oqxU521xW9h8rJWzVWxD4",
        "analysis_url": "https://api.spotify.com/v1/audio-analysis/1oqxU521xW9h8rJWzVWxD4",
        "duration_ms": 167933,
        "time_signature": 4
    },
    {
        "danceability": 0.548,
        "energy": 0.912,
        "key": 7,
        "loudness": -7.336,
        "mode": 1,
        "speechiness": 0.0582,
        "acousticness": 0.177,
        "instrumentalness": 0.499,
        "liveness": 0.144,
        "valence": 0.779,
        "tempo": 127.639,
        "type": "audio_features",
        "id": "3hQ51c9dPj9FcSdOHhrfkq",
        "uri": "spotify:track:3hQ51c9dPj9FcSdOHhrfkq",
        "track_href": "https://api.spotify.com/v1/tracks/3hQ51c9dPj9FcSdOHhrfkq",
        "analysis_url": "https://api.spotify.com/v1/audio-analysis/3hQ51c9dPj9FcSdOHhrfkq",
        "duration_ms": 156178,
        "time_signature": 4
    },
    {
        "danceability": 0.675,
        "energy": 0.364,
        "key": 0,
        "loudness": -13.561,
        "mode": 0,
        "speechiness": 0.919,
        "acousticness": 0.623,
        "instrumentalness": 0,
        "liveness": 0.125,
        "valence": 0.598,
        "tempo": 72.74,
        "type": "audio_features",
        "id": "5wwKRbqWdHVNNkJOIxXWMf",
        "uri": "spotify:track:5wwKRbqWdHVNNkJOIxXWMf",
        "track_href": "https://api.spotify.com/v1/tracks/5wwKRbqWdHVNNkJOIxXWMf",
        "analysis_url": "https://api.spotify.com/v1/audio-analysis/5wwKRbqWdHVNNkJOIxXWMf",
        "duration_ms": 543067,
        "time_signature": 4
    },
    {
        "danceability": 0.64,
        "energy": 0.748,
        "key": 4,
        "loudness": -2.947,
        "mode": 0,
        "speechiness": 0.123,
        "acousticness": 0.00466,
        "instrumentalness": 0,
        "liveness": 0.326,
        "valence": 0.0792,
        "tempo": 67.52,
        "type": "audio_features",
        "id": "7oKZFdtsovhKzBNAlUu7kC",
        "uri": "spotify:track:7oKZFdtsovhKzBNAlUu7kC",
        "track_href": "https://api.spotify.com/v1/tracks/7oKZFdtsovhKzBNAlUu7kC",
        "analysis_url": "https://api.spotify.com/v1/audio-analysis/7oKZFdtsovhKzBNAlUu7kC",
        "duration_ms": 188402,
        "time_signature": 4
    },
    {
        "danceability": 0.679,
        "energy": 0.565,
        "key": 3,
        "loudness": -12.405,
        "mode": 1,
        "speechiness": 0.0896,
        "acousticness": 0.68,
        "instrumentalness": 2.64e-05,
        "liveness": 0.0509,
        "valence": 0.965,
        "tempo": 115.432,
        "type": "audio_features",
        "id": "3ncplTQUYBcxi2cCTiqvKC",
        "uri": "spotify:track:3ncplTQUYBcxi2cCTiqvKC",
        "track_href": "https://api.spotify.com/v1/tracks/3ncplTQUYBcxi2cCTiqvKC",
        "analysis_url": "https://api.spotify.com/v1/audio-analysis/3ncplTQUYBcxi2cCTiqvKC",
        "duration_ms": 194400,
        "time_signature": 4
    },
    {
        "danceability": 0.433,
        "energy": 0.465,
        "key": 3,
        "loudness": -10.427,
        "mode": 1,
        "speechiness": 0.0253,
        "acousticness": 0.512,
        "instrumentalness": 0.285,
        "liveness": 0.258,
        "valence": 0.75,
        "tempo": 83.757,
        "type": "audio_features",
        "id": "4Bum7VuVFzfXPHb3VF9GFB",
        "uri": "spotify:track:4Bum7VuVFzfXPHb3VF9GFB",
        "track_href": "https://api.spotify.com/v1/tracks/4Bum7VuVFzfXPHb3VF9GFB",
        "analysis_url": "https://api.spotify.com/v1/audio-analysis/4Bum7VuVFzfXPHb3VF9GFB",
        "duration_ms": 174864,
        "time_signature": 4
    },
    {
        "danceability": 0.447,
        "energy": 0.319,
        "key": 8,
        "loudness": -10.732,
        "mode": 1,
        "speechiness": 0.0264,
        "acousticness": 0.63,
        "instrumentalness": 1.35e-06,
        "liveness": 0.106,
        "valence": 0.246,
        "tempo": 162.109,
        "type": "audio_features",
        "id": "6MnDkyb3VstTCT9ELxjfeE",
        "uri": "spotify:track:6MnDkyb3VstTCT9ELxjfeE",
        "track_href": "https://api.spotify.com/v1/tracks/6MnDkyb3VstTCT9ELxjfeE",
        "analysis_url": "https://api.spotify.com/v1/audio-analysis/6MnDkyb3VstTCT9ELxjfeE",
        "duration_ms": 241307,
        "time_signature": 4
    },
    {
        "danceability": 0.691,
        "energy": 0.853,
        "key": 1,
        "loudness": -2.528,
        "mode": 0,
        "speechiness": 0.0372,
        "acousticness": 0.0631,
        "instrumentalness": 7.13e-05,
        "liveness": 0.082,
        "valence": 0.762,
        "tempo": 145.999,
        "type": "audio_features",
        "id": "6eDApnV9Jdb1nYahOlbbUh",
        "uri": "spotify:track:6eDApnV9Jdb1nYahOlbbUh",
        "track_href": "https://api.spotify.com/v1/tracks/6eDApnV9Jdb1nYahOlbbUh",
        "analysis_url": "https://api.spotify.com/v1/audio-analysis/6eDApnV9Jdb1nYahOlbbUh",
        "duration_ms": 215867,
        "time_signature": 4
    },
    {
        "danceability": 0.461,
        "energy": 0.73,
        "key": 9,
        "loudness": -3.262,
        "mode": 1,
        "speechiness": 0.0371,
        "acousticness": 0.295,
        "instrumentalness": 4.31e-06,
        "liveness": 0.383,
        "valence": 0.253,
        "tempo": 145.197,
        "type": "audio_features",
        "id": "6cC9RY7MoUx5z3aHjDTNI6",
        "uri": "spotify:track:6cC9RY7MoUx5z3aHjDTNI6",
        "track_href": "https://api.spotify.com/v1/tracks/6cC9RY7MoUx5z3aHjDTNI6",
        "analysis_url": "https://api.spotify.com/v1/audio-analysis/6cC9RY7MoUx5z3aHjDTNI6",
        "duration_ms": 271013,
        "time_signature": 4
    },
    {
        "danceability": 0.679,
        "energy": 0.374,
        "key": 11,
        "loudness": -10.565,
        "mode": 0,
        "speechiness": 0.0482,
        "acousticness": 0.402,
        "instrumentalness": 2.49e-05,
        "liveness": 0.0541,
        "valence": 0.871,
        "tempo": 80.86,
        "type": "audio_features",
        "id": "1tL5a9jowsWMtn3wkFYsG9",
        "uri": "spotify:track:1tL5a9jowsWMtn3wkFYsG9",
        "track_href": "https://api.spotify.com/v1/tracks/1tL5a9jowsWMtn3wkFYsG9",
        "analysis_url": "https://api.spotify.com/v1/audio-analysis/1tL5a9jowsWMtn3wkFYsG9",
        "duration_ms": 306800,
        "time_signature": 4
    },
    {
        "danceability": 0.311,
        "energy": 0.582,
        "key": 7,
        "loudness": -10.894,
        "mode": 0,
        "speechiness": 0.0651,
        "acousticness": 0.126,
        "instrumentalness": 0.00542,
        "liveness": 0.12,
        "valence": 0.578,
        "tempo": 184.679,
        "type": "audio_features",
        "id": "09athuEe5kQfC7bV63jmGa",
        "uri": "spotify:track:09athuEe5kQfC7bV63jmGa",
        "track_href": "https://api.spotify.com/v1/tracks/09athuEe5kQfC7bV63jmGa",
        "analysis_url": "https://api.spotify.com/v1/audio-analysis/09athuEe5kQfC7bV63jmGa",
        "duration_ms": 265760,
        "time_signature": 4
    },
    {
        "danceability": 0.559,
        "energy": 0.499,
        "key": 5,
        "loudness": -10.131,
        "mode": 0,
        "speechiness": 0.0347,
        "acousticness": 0.725,
        "instrumentalness": 0.179,
        "liveness": 0.116,
        "valence": 0.773,
        "tempo": 151.423,
        "type": "audio_features",
        "id": "7edHx31pS8lQtjvvn06m6x",
        "uri": "spotify:track:7edHx31pS8lQtjvvn06m6x",
        "track_href": "https://api.spotify.com/v1/tracks/7edHx31pS8lQtjvvn06m6x",
        "analysis_url": "https://api.spotify.com/v1/audio-analysis/7edHx31pS8lQtjvvn06m6x",
        "duration_ms": 124992,
        "time_signature": 4
    },
    {
        "danceability": 0.587,
        "energy": 0.767,
        "key": 0,
        "loudness": -5.713,
        "mode": 1,
        "speechiness": 0.0449,
        "acousticness": 0.225,
        "instrumentalness": 0,
        "liveness": 0.112,
        "valence": 0.664,
        "tempo": 100.38,
        "type": "audio_features",
        "id": "5p9XWUdvbUzmPCukOmwoU3",
        "uri": "spotify:track:5p9XWUdvbUzmPCukOmwoU3",
        "track_href": "https://api.spotify.com/v1/tracks/5p9XWUdvbUzmPCukOmwoU3",
        "analysis_url": "https://api.spotify.com/v1/audio-analysis/5p9XWUdvbUzmPCukOmwoU3",
        "duration_ms": 201707,
        "time_signature": 4
    },
    {
        "danceability": 0.735,
        "energy": 0.735,
        "key": 2,
        "loudness": -4.322,
        "mode": 1,
        "speechiness": 0.0458,
        "acousticness": 0.145,
        "instrumentalness": 6.83e-06,
        "liveness": 0.057,
        "valence": 0.979,
        "tempo": 150.297,
        "type": "audio_features",
        "id": "35iVqFnqmcqbIckOYoFnrn",
        "uri": "spotify:track:35iVqFnqmcqbIckOYoFnrn",
        "track_href": "https://api.spotify.com/v1/tracks/35iVqFnqmcqbIckOYoFnrn",
        "analysis_url": "https://api.spotify.com/v1/audio-analysis/35iVqFnqmcqbIckOYoFnrn",
        "duration_ms": 155987,
        "time_signature": 4
    },
    {
        "danceability": 0.678,
        "energy": 0.911,
        "key": 11,
        "loudness": -3.847,
        "mode": 0,
        "speechiness": 0.0525,
        "acousticness": 0.0217,
        "instrumentalness": 0,
        "liveness": 0.356,
        "valence": 0.859,
        "tempo": 135.916,
        "type": "audio_features",
        "id": "1p5VeCCFyeafMMDaXak10E",
        "uri": "spotify:track:1p5VeCCFyeafMMDaXak10E",
        "track_href": "https://api.spotify.com/v1/tracks/1p5VeCCFyeafMMDaXak10E",
        "analysis_url": "https://api.spotify.com/v1/audio-analysis/1p5VeCCFyeafMMDaXak10E",
        "duration_ms": 179742,
        "time_signature": 4
    },
    {
        "danceability": 0.565,
        "energy": 0.308,
        "key": 7,
        "loudness": -11.841,
        "mode": 1,
        "speechiness": 0.0269,
        "acousticness": 0.919,
        "instrumentalness": 0.00139,
        "liveness": 0.312,
        "valence": 0.454,
        "tempo": 82.761,
        "type": "audio_features",
        "id": "7KjsPUMEiwqkAPm8G5hjrA",
        "uri": "spotify:track:7KjsPUMEiwqkAPm8G5hjrA",
        "track_href": "https://api.spotify.com/v1/tracks/7KjsPUMEiwqkAPm8G5hjrA",
        "analysis_url": "https://api.spotify.com/v1/audio-analysis/7KjsPUMEiwqkAPm8G5hjrA",
        "duration_ms": 149907,
        "time_signature": 3
    },
    {
        "danceability": 0.513,
        "energy": 0.425,
        "key": 8,
        "loudness": -13.935,
        "mode": 1,
        "speechiness": 0.033,
        "acousticness": 0.713,
        "instrumentalness": 0,
        "liveness": 0.082,
        "valence": 0.96,
        "tempo": 174.309,
        "type": "audio_features",
        "id": "39J4fonR8sQR8dPmMXYGNX",
        "uri": "spotify:track:39J4fonR8sQR8dPmMXYGNX",
        "track_href": "https://api.spotify.com/v1/tracks/39J4fonR8sQR8dPmMXYGNX",
        "analysis_url": "https://api.spotify.com/v1/audio-analysis/39J4fonR8sQR8dPmMXYGNX",
        "duration_ms": 157133,
        "time_signature": 4
    },
    {
        "danceability": 0.611,
        "energy": 0.635,
        "key": 5,
        "loudness": -5.795,
        "mode": 1,
        "speechiness": 0.0646,
        "acousticness": 0.786,
        "instrumentalness": 0,
        "liveness": 0.0832,
        "valence": 0.891,
        "tempo": 76.01,
        "type": "audio_features",
        "id": "3hkshi6R4qAoKHNVnApeyh",
        "uri": "spotify:track:3hkshi6R4qAoKHNVnApeyh",
        "track_href": "https://api.spotify.com/v1/tracks/3hkshi6R4qAoKHNVnApeyh",
        "analysis_url": "https://api.spotify.com/v1/audio-analysis/3hkshi6R4qAoKHNVnApeyh",
        "duration_ms": 135800,
        "time_signature": 4
    },
    {
        "danceability": 0.726,
        "energy": 0.474,
        "key": 1,
        "loudness": -7.834,
        "mode": 0,
        "speechiness": 0.0491,
        "acousticness": 0.803,
        "instrumentalness": 0,
        "liveness": 0.258,
        "valence": 0.57,
        "tempo": 116.027,
        "type": "audio_features",
        "id": "0AQquaENerGps8BQmbPw14",
        "uri": "spotify:track:0AQquaENerGps8BQmbPw14",
        "track_href": "https://api.spotify.com/v1/tracks/0AQquaENerGps8BQmbPw14",
        "analysis_url": "https://api.spotify.com/v1/audio-analysis/0AQquaENerGps8BQmbPw14",
        "duration_ms": 235733,
        "time_signature": 4
    },
    {
        "danceability": 0.425,
        "energy": 0.783,
        "key": 8,
        "loudness": -9.077,
        "mode": 1,
        "speechiness": 0.0808,
        "acousticness": 0.00631,
        "instrumentalness": 0.852,
        "liveness": 0.0745,
        "valence": 0.422,
        "tempo": 106.281,
        "type": "audio_features",
        "id": "2Xtsv7BUMrNodQWH2JPOc0",
        "uri": "spotify:track:2Xtsv7BUMrNodQWH2JPOc0",
        "track_href": "https://api.spotify.com/v1/tracks/2Xtsv7BUMrNodQWH2JPOc0",
        "analysis_url": "https://api.spotify.com/v1/audio-analysis/2Xtsv7BUMrNodQWH2JPOc0",
        "duration_ms": 555000,
        "time_signature": 3
    },
    {
        "danceability": 0.604,
        "energy": 0.105,
        "key": 2,
        "loudness": -16.78,
        "mode": 1,
        "speechiness": 0.0357,
        "acousticness": 0.977,
        "instrumentalness": 0,
        "liveness": 0.0993,
        "valence": 0.553,
        "tempo": 92.238,
        "type": "audio_features",
        "id": "0gssZyDIxrn2CsokEML0xq",
        "uri": "spotify:track:0gssZyDIxrn2CsokEML0xq",
        "track_href": "https://api.spotify.com/v1/tracks/0gssZyDIxrn2CsokEML0xq",
        "analysis_url": "https://api.spotify.com/v1/audio-analysis/0gssZyDIxrn2CsokEML0xq",
        "duration_ms": 141120,
        "time_signature": 4
    },
    {
        "danceability": 0.524,
        "energy": 0.553,
        "key": 0,
        "loudness": -10.767,
        "mode": 1,
        "speechiness": 0.0292,
        "acousticness": 0.831,
        "instrumentalness": 0,
        "liveness": 0.174,
        "valence": 0.517,
        "tempo": 104.578,
        "type": "audio_features",
        "id": "4hupcimlg3UBbW1kAQ6vrT",
        "uri": "spotify:track:4hupcimlg3UBbW1kAQ6vrT",
        "track_href": "https://api.spotify.com/v1/tracks/4hupcimlg3UBbW1kAQ6vrT",
        "analysis_url": "https://api.spotify.com/v1/audio-analysis/4hupcimlg3UBbW1kAQ6vrT",
        "duration_ms": 196493,
        "time_signature": 4
    },
    {
        "danceability": 0.547,
        "energy": 0.32,
        "key": 5,
        "loudness": -20.554,
        "mode": 1,
        "speechiness": 0.0668,
        "acousticness": 0.831,
        "instrumentalness": 0.939,
        "liveness": 0.111,
        "valence": 0.316,
        "tempo": 180.034,
        "type": "audio_features",
        "id": "0ktCvcAGHl8pPXJY23QaAn",
        "uri": "spotify:track:0ktCvcAGHl8pPXJY23QaAn",
        "track_href": "https://api.spotify.com/v1/tracks/0ktCvcAGHl8pPXJY23QaAn",
        "analysis_url": "https://api.spotify.com/v1/audio-analysis/0ktCvcAGHl8pPXJY23QaAn",
        "duration_ms": 117333,
        "time_signature": 4
    },
    {
        "danceability": 0.577,
        "energy": 0.956,
        "key": 5,
        "loudness": -3.594,
        "mode": 1,
        "speechiness": 0.0557,
        "acousticness": 0.657,
        "instrumentalness": 0,
        "liveness": 0.28,
        "valence": 0.761,
        "tempo": 91.345,
        "type": "audio_features",
        "id": "3NVSL82aaHTdjtk2ujpS1C",
        "uri": "spotify:track:3NVSL82aaHTdjtk2ujpS1C",
        "track_href": "https://api.spotify.com/v1/tracks/3NVSL82aaHTdjtk2ujpS1C",
        "analysis_url": "https://api.spotify.com/v1/audio-analysis/3NVSL82aaHTdjtk2ujpS1C",
        "duration_ms": 127613,
        "time_signature": 4
    },
    {
        "danceability": 0.352,
        "energy": 0.317,
        "key": 0,
        "loudness": -8.694,
        "mode": 1,
        "speechiness": 0.0308,
        "acousticness": 0.861,
        "instrumentalness": 0,
        "liveness": 0.136,
        "valence": 0.506,
        "tempo": 133.113,
        "type": "audio_features",
        "id": "3G7spgNysEke1Fr8ZYYbwg",
        "uri": "spotify:track:3G7spgNysEke1Fr8ZYYbwg",
        "track_href": "https://api.spotify.com/v1/tracks/3G7spgNysEke1Fr8ZYYbwg",
        "analysis_url": "https://api.spotify.com/v1/audio-analysis/3G7spgNysEke1Fr8ZYYbwg",
        "duration_ms": 160440,
        "time_signature": 4
    },
    {
        "danceability": 0.514,
        "energy": 0.892,
        "key": 7,
        "loudness": -3.36,
        "mode": 1,
        "speechiness": 0.0377,
        "acousticness": 1.84e-05,
        "instrumentalness": 0.927,
        "liveness": 0.241,
        "valence": 0.865,
        "tempo": 136.028,
        "type": "audio_features",
        "id": "2t5cAV9ypFGJUrj695nM5F",
        "uri": "spotify:track:2t5cAV9ypFGJUrj695nM5F",
        "track_href": "https://api.spotify.com/v1/tracks/2t5cAV9ypFGJUrj695nM5F",
        "analysis_url": "https://api.spotify.com/v1/audio-analysis/2t5cAV9ypFGJUrj695nM5F",
        "duration_ms": 123813,
        "time_signature": 4
    },
    {
        "danceability": 0.63,
        "energy": 0.754,
        "key": 2,
        "loudness": -3.564,
        "mode": 1,
        "speechiness": 0.0284,
        "acousticness": 0.0963,
        "instrumentalness": 0,
        "liveness": 0.268,
        "valence": 0.73,
        "tempo": 95.999,
        "type": "audio_features",
        "id": "0bPnT6i9H1p8Vd85GS6Z7I",
        "uri": "spotify:track:0bPnT6i9H1p8Vd85GS6Z7I",
        "track_href": "https://api.spotify.com/v1/tracks/0bPnT6i9H1p8Vd85GS6Z7I",
        "analysis_url": "https://api.spotify.com/v1/audio-analysis/0bPnT6i9H1p8Vd85GS6Z7I",
        "duration_ms": 172253,
        "time_signature": 4
    },
    {
        "danceability": 0.32,
        "energy": 0.17,
        "key": 9,
        "loudness": -11.699,
        "mode": 1,
        "speechiness": 0.036,
        "acousticness": 0.924,
        "instrumentalness": 4.16e-05,
        "liveness": 0.0993,
        "valence": 0.208,
        "tempo": 196.12,
        "type": "audio_features",
        "id": "0J10lTnQV1rosvX0jYYX5J",
        "uri": "spotify:track:0J10lTnQV1rosvX0jYYX5J",
        "track_href": "https://api.spotify.com/v1/tracks/0J10lTnQV1rosvX0jYYX5J",
        "analysis_url": "https://api.spotify.com/v1/audio-analysis/0J10lTnQV1rosvX0jYYX5J",
        "duration_ms": 258393,
        "time_signature": 3
    },
    {
        "danceability": 0.739,
        "energy": 0.586,
        "key": 10,
        "loudness": -5.079,
        "mode": 0,
        "speechiness": 0.0472,
        "acousticness": 0.0245,
        "instrumentalness": 0.000252,
        "liveness": 0.308,
        "valence": 0.444,
        "tempo": 124.026,
        "type": "audio_features",
        "id": "1bgKMxPQU7JIZEhNsM1vFs",
        "uri": "spotify:track:1bgKMxPQU7JIZEhNsM1vFs",
        "track_href": "https://api.spotify.com/v1/tracks/1bgKMxPQU7JIZEhNsM1vFs",
        "analysis_url": "https://api.spotify.com/v1/audio-analysis/1bgKMxPQU7JIZEhNsM1vFs",
        "duration_ms": 142677,
        "time_signature": 4
    }
]